<?xml version="1.0" encoding="UTF-8" standalone="no" ?>
<Mission xmlns="http://ProjectMalmo.microsoft.com"
         xmlns:xsi="http://www.w3.org/2001/XMLSchema-instance">
  <About>
    <Summary>Activley Sampling BC Policy</Summary>
  </About>
  <ServerSection>
    <ServerInitialConditions>
        <Time>
            <StartTime>10000</StartTime>
        </Time>
        <Weather>clear</Weather>
    </ServerInitialConditions>
    <ServerHandlers>
      <FlatWorldGenerator generatorString="3;7,2;1;" forceReset="true"/>
      <DrawingDecorator>
        <DrawCuboid x1="50" y1="2" z1="0" x2="60" y2="102" z2="10" type="gold_block"/>
      </DrawingDecorator>
      <ServerQuitFromTimeUp timeLimitMs="60000"/>
      <ServerQuitWhenAnyAgentFinishes/>
    </ServerHandlers>
  </ServerSection>
  
  

  <AgentSection mode="Survival">
    <Name>Navigator</Name>
    <AgentStart>
      <Placement x="30" y="2" z="5" yaw="90"/>
    </AgentStart>
    <AgentHandlers>
      <ObservationFromFullStats/>
      <ContinuousMovementCommands turnSpeedDegs="180"/>
      <AgentQuitFromTouchingBlockType>
        <Block type="gold_block"/>
      </AgentQuitFromTouchingBlockType>
    </AgentHandlers>
  </AgentSection>
</Mission>